gemstone/__init__.py
gemstone/cli.py
gemstone/errors.py
gemstone/util.py
gemstone/__pycache__/__init__.cpython-36.pyc
gemstone/auth/__init__.py
gemstone/auth/base/__init__.py
gemstone/auth/base/validation_strategy.py
gemstone/auth/validation_strategies/__init__.py
gemstone/auth/validation_strategies/basic_cookie_strategy.py
gemstone/auth/validation_strategies/header_strategy.py
gemstone/client/__init__.py
gemstone/client/remote_service.py
gemstone/client/structs.py
gemstone/config/__init__.py
gemstone/config/configurable.py
gemstone/config/configurator.py
gemstone/core/__init__.py
gemstone/core/container.py
gemstone/core/decorators.py
gemstone/core/handlers.py
gemstone/core/microservice.py
gemstone/core/stats.py
gemstone/core/structs.py
gemstone/discovery/__init__.py
gemstone/discovery/base.py
gemstone/discovery/cache.py
gemstone/discovery/default.py
gemstone/discovery/redis_strategy.py
gemstone/event/__init__.py
gemstone/event/transport/__init__.py
gemstone/event/transport/base.py
gemstone/event/transport/rabbitmq.py
gemstone/event/transport/redis_transport.py
gemstone/plugins/__init__.py
gemstone/plugins/base.py
gemstone/plugins/error.py
gemstone-0.12.0.dist-info/DESCRIPTION.rst
gemstone-0.12.0.dist-info/METADATA
gemstone-0.12.0.dist-info/RECORD
gemstone-0.12.0.dist-info/WHEEL
gemstone-0.12.0.dist-info/metadata.json
gemstone-0.12.0.dist-info/top_level.txt
tests/__init__.py
tests/test_client.py
tests/test_client_functional.py
tests/test_jsonrpc_specs.py
tests/test_microservice.py
tests/test_pymicroservice.py
tests/test_service_creation.py
tests/test_service_registry_integration.py
tests/test_structs.py
tests/test_utils.py
tests/configuration/__init__.py
tests/configuration/test_cmd_configuration.py
tests/configuration/test_configurables.py
tests/functional/__init__.py
tests/functional/test_jsonrpc_specs.py
tests/functional/test_microservice.py
tests/services/__init__.py
tests/services/service_client.py
tests/services/service_jsonrpc_specs.py
tests/services/service_microservice.py
tests/services/service_service_creation.py
tests/services/service_service_registry_integration.py
tests/services/service_validation_strategies.py
