Metadata-Version: 1.1
Name: gemstone
Version: 0.12.0
Summary: Build microservices with Python
Home-page: https://github.com/vladcalin/gemstone
Author: Vlad Calin
Author-email: vlad.s.calin@gmail.com
License: MIT
Keywords: microservice,service,gemstone,jsonrpc,rpc,http,asynchronous,async,tornado
Platform: UNKNOWN
Classifier: Development Status :: 3 - Alpha
Classifier: License :: OSI Approved :: MIT License
Classifier: Operating System :: OS Independent
Classifier: Topic :: Utilities
Classifier: Programming Language :: Python :: 3.4
Classifier: Programming Language :: Python :: 3.5
Classifier: Programming Language :: Python :: 3.6
